radas/__init__.py
radas/adas_interface/__init__.py
radas/adas_interface/determine_adas_dataset_type.py
radas/adas_interface/download_adas_datasets.py
radas/adas_interface/fortran_reader.py
radas/adas_interface/read_adf11_file.py
radas/cli.py
radas/config.yaml
radas/coronal_equilibrium.py
radas/interpolate_rates.py
radas/mavrin_reference/__init__.py
radas/mavrin_reference/compare_to_mavrin.py
radas/mavrin_reference/mavrin_data.yaml
radas/mavrin_reference/read_mavrin_data.py
radas/radiated_power.py
radas/read_rate_coeffs.py
radas/shared.py
radas/time_evolution.py
radas/unit_handling.py
radas-2025.6.2.dist-info/LICENSE
radas-2025.6.2.dist-info/METADATA
radas-2025.6.2.dist-info/WHEEL
radas-2025.6.2.dist-info/entry_points.txt
radas-2025.6.2.dist-info/RECORD
