Metadata-Version: 2.1
Name: radas
Version: 2025.6.2
Summary: Plasma radiated power calculated using OpenADAS
Author: Commonwealth Fusion Systems
Requires-Python: >=3.10
Classifier: Development Status :: 5 - Production/Stable
Classifier: Intended Audience :: Science/Research
Classifier: License :: OSI Approved :: MIT License
Classifier: Programming Language :: Python :: 3
Classifier: Programming Language :: Python :: 3.10
Classifier: Programming Language :: Python :: 3.11
Classifier: Programming Language :: Python :: 3.12
Classifier: Programming Language :: Python :: 3 :: Only
Classifier: Topic :: Scientific/Engineering :: Physics
Requires-Dist: Pint (>=0.21)
Requires-Dist: click (>=8.1)
Requires-Dist: fortranformat (>=2.0.0)
Requires-Dist: matplotlib (>=3.6)
Requires-Dist: meson (>=1.5.0)
Requires-Dist: ninja (>=1.11.1.1)
Requires-Dist: numpy (>=1.22)
Requires-Dist: pint-xarray (>=0.3)
Requires-Dist: pyyaml (>=6.0)
Requires-Dist: scipy (>=1.8)
Requires-Dist: xarray (>=2023)
